inspect_agents-0.0.2.dist-info/METADATA
inspect_agents-0.0.2.dist-info/WHEEL
inspect_agents-0.0.2.dist-info/entry_points.txt
inspect_agents-0.0.2.dist-info/licenses/LICENSE
inspect_agents/__init__.py
inspect_agents/_conversation.py
inspect_agents/_model_retry.py
inspect_agents/agents.py
inspect_agents/approval.py
inspect_agents/config.py
inspect_agents/exceptions.py
inspect_agents/files_models.py
inspect_agents/files_ops_sandbox.py
inspect_agents/files_ops_store.py
inspect_agents/filters.py
inspect_agents/fs.py
inspect_agents/fs_adapter.py
inspect_agents/iterative.py
inspect_agents/iterative_config.py
inspect_agents/iterative_runtime.py
inspect_agents/logging.py
inspect_agents/migration.py
inspect_agents/model.py
inspect_agents/my_helper.py
inspect_agents/observability.py
inspect_agents/profiles.py
inspect_agents/run.py
inspect_agents/schema.py
inspect_agents/settings.py
inspect_agents/state.py
inspect_agents/tool_types.py
inspect_agents/tools.py
inspect_agents/tools_files.py
inspect_agents-0.0.2.dist-info/RECORD
