Metadata-Version: 2.1
Name: inspect-agents
Version: 0.0.2
Summary: Inspect-AI–based agents and tools.
License: MIT
Project-URL: Homepage, https://github.com/cnm13ryan/inspect_agents
Project-URL: Documentation, https://cnm13ryan.github.io/inspect_agents
Project-URL: Repository, https://github.com/cnm13ryan/inspect_agents.git
Project-URL: Issues, https://github.com/cnm13ryan/inspect_agents/issues
Requires-Python: <4.0,>=3.11
Requires-Dist: inspect-ai>=0.3.129
Requires-Dist: jsonlines>=4.0.0
Requires-Dist: openai>=1.104.1
Requires-Dist: requests>=2.32.5
Requires-Dist: tavily-python>=0.7.11
Provides-Extra: dev
Requires-Dist: ruff<0.13.0,>=0.9.6; extra == "dev"
Requires-Dist: pyright==1.1.401; extra == "dev"
Requires-Dist: pre-commit; extra == "dev"
Provides-Extra: testing
Requires-Dist: pytest==8.3.5; extra == "testing"
Requires-Dist: pytest-asyncio==0.26.0; extra == "testing"
Requires-Dist: pytest-mock==3.14.0; extra == "testing"
Requires-Dist: pytest-benchmark==4.0.0; extra == "testing"
Requires-Dist: pytest-xdist; extra == "testing"
Requires-Dist: pytest-cov==6.1.1; extra == "testing"
Requires-Dist: coverage[toml]; extra == "testing"
Requires-Dist: hypothesis==6.131.10; extra == "testing"
Provides-Extra: utilities
Requires-Dist: python-dotenv==1.0.0; extra == "utilities"
Requires-Dist: PyYAML; extra == "utilities"
Requires-Dist: retry==0.9.2; extra == "utilities"
Requires-Dist: nbformat; extra == "utilities"
Provides-Extra: docs
Requires-Dist: mkdocs>=1.5; extra == "docs"
Requires-Dist: mkdocs-material>=9.0; extra == "docs"
Requires-Dist: mkdocs-mermaid2-plugin; extra == "docs"
Requires-Dist: mkdocs-autorefs>=1.0; extra == "docs"
Requires-Dist: mkdocs-redirects>=1.2.1; extra == "docs"
Requires-Dist: mkdocs-exclude-search>=0.6.5; extra == "docs"
Requires-Dist: mkdocs-minify-plugin; extra == "docs"
Requires-Dist: mkdocs-click; extra == "docs"
Requires-Dist: mkdocs-glightbox>=0.3.4; extra == "docs"
Requires-Dist: mkdocs-git-revision-date-localized-plugin; extra == "docs"
Requires-Dist: mkdocs-htmlproofer-plugin>=1.2.0; extra == "docs"
Requires-Dist: mkdocstrings[python]>=0.21; extra == "docs"
Requires-Dist: mike>=2.0.0; extra == "docs"
Requires-Dist: interrogate; extra == "docs"
